{
 "cells": [
  {
   "cell_type": "code",
   "execution_count": 2,
   "metadata": {},
   "outputs": [],
   "source": [
    "# Lists vs Tuples"
   ]
  },
  {
   "cell_type": "code",
   "execution_count": 2,
   "metadata": {},
   "outputs": [],
   "source": [
    "# dis stands for disassemble\n",
    "from dis import dis"
   ]
  },
  {
   "cell_type": "code",
   "execution_count": 4,
   "metadata": {},
   "outputs": [
    {
     "name": "stdout",
     "output_type": "stream",
     "text": [
      "  1           0 LOAD_CONST               0 ((1, 2, 'a'))\n",
      "              2 RETURN_VALUE\n"
     ]
    }
   ],
   "source": [
    "dis(compile(\"(1, 2, 'a')\", 'string', 'eval'))"
   ]
  },
  {
   "cell_type": "code",
   "execution_count": 3,
   "metadata": {},
   "outputs": [
    {
     "name": "stdout",
     "output_type": "stream",
     "text": [
      "  1           0 LOAD_CONST               0 (1)\n",
      "              2 LOAD_CONST               1 (2)\n",
      "              4 LOAD_CONST               2 (3)\n",
      "              6 BUILD_LIST               3\n",
      "              8 RETURN_VALUE\n"
     ]
    }
   ],
   "source": [
    "dis(compile('[1, 2, 3]', 'string', 'eval')) # has to load each element in the list"
   ]
  },
  {
   "cell_type": "code",
   "execution_count": 6,
   "metadata": {},
   "outputs": [
    {
     "name": "stdout",
     "output_type": "stream",
     "text": [
      "  1           0 LOAD_CONST               0 (1)\n",
      "              2 LOAD_CONST               1 (2)\n",
      "              4 BUILD_LIST               2\n",
      "              6 LOAD_CONST               2 ((9, 8))\n",
      "              8 BUILD_TUPLE              2\n",
      "             10 RETURN_VALUE\n"
     ]
    }
   ],
   "source": [
    "dis(compile('([1, 2], (9, 8))', 'string', 'eval')) # if a tuple contains a list, it will still have to build it up"
   ]
  },
  {
   "cell_type": "code",
   "execution_count": 7,
   "metadata": {},
   "outputs": [],
   "source": [
    "from timeit import timeit"
   ]
  },
  {
   "cell_type": "code",
   "execution_count": 8,
   "metadata": {},
   "outputs": [
    {
     "data": {
      "text/plain": [
       "0.1449058550006157"
      ]
     },
     "execution_count": 8,
     "metadata": {},
     "output_type": "execute_result"
    }
   ],
   "source": [
    "timeit('(1,2, 3,4,5,8)', number=10_000_000) # more efficient"
   ]
  },
  {
   "cell_type": "code",
   "execution_count": 10,
   "metadata": {},
   "outputs": [
    {
     "data": {
      "text/plain": [
       "0.8039844739996624"
      ]
     },
     "execution_count": 10,
     "metadata": {},
     "output_type": "execute_result"
    }
   ],
   "source": [
    "timeit('[1, 2, 3, 4]', number=10_000_000) # much slower"
   ]
  },
  {
   "cell_type": "code",
   "execution_count": 12,
   "metadata": {},
   "outputs": [
    {
     "data": {
      "text/plain": [
       "0.7258900529996026"
      ]
     },
     "execution_count": 12,
     "metadata": {},
     "output_type": "execute_result"
    }
   ],
   "source": [
    "timeit('([1, 2, 3, 4])', number=10_000_000) # still slow if the tuple contains mutable types"
   ]
  },
  {
   "cell_type": "code",
   "execution_count": 13,
   "metadata": {},
   "outputs": [],
   "source": [
    "def fn():\n",
    "    pass"
   ]
  },
  {
   "cell_type": "code",
   "execution_count": 20,
   "metadata": {},
   "outputs": [
    {
     "name": "stdout",
     "output_type": "stream",
     "text": [
      "  1           0 LOAD_NAME                0 (fn)\n",
      "              2 LOAD_CONST               0 (10)\n",
      "              4 LOAD_CONST               1 (20)\n",
      "              6 LOAD_CONST               2 (30)\n",
      "              8 BUILD_TUPLE              4\n",
      "             10 RETURN_VALUE\n"
     ]
    }
   ],
   "source": [
    "dis(compile('(fn, 10, 20, 30)', 'string', 'eval')) # if there is a fn, it will have to load all"
   ]
  },
  {
   "cell_type": "code",
   "execution_count": 27,
   "metadata": {},
   "outputs": [
    {
     "name": "stdout",
     "output_type": "stream",
     "text": [
      "  1           0 BUILD_LIST               0\n",
      "              2 LOAD_CONST               0 (10)\n",
      "              4 LOAD_CONST               1 (20)\n",
      "              6 LOAD_CONST               2 (30)\n",
      "              8 LOAD_CONST               3 ((3, 8, 'a'))\n",
      "             10 BUILD_TUPLE              5\n",
      "             12 RETURN_VALUE\n"
     ]
    }
   ],
   "source": [
    "dis(compile('([], 10, 20, 30, (3, 8, \"a\"))', 'string', 'eval')) # if there is a fn, it will have to load all"
   ]
  },
  {
   "cell_type": "code",
   "execution_count": 33,
   "metadata": {},
   "outputs": [],
   "source": [
    "l1 = [1, 2, 3, 4, 5]\n",
    "t1 = 1, 2, 3, 4, 5\n",
    "id_l, id_t = id(l1), id(t1) "
   ]
  },
  {
   "cell_type": "code",
   "execution_count": 37,
   "metadata": {},
   "outputs": [
    {
     "data": {
      "text/plain": [
       "(False, True)"
      ]
     },
     "execution_count": 37,
     "metadata": {},
     "output_type": "execute_result"
    }
   ],
   "source": [
    "l2 = list(l1)\n",
    "l1 is l2, l1[0] is l2[0] # created a new list, shallow copy"
   ]
  },
  {
   "cell_type": "code",
   "execution_count": 39,
   "metadata": {},
   "outputs": [
    {
     "data": {
      "text/plain": [
       "True"
      ]
     },
     "execution_count": 39,
     "metadata": {},
     "output_type": "execute_result"
    }
   ],
   "source": [
    "t2 = tuple(t1)\n",
    "t2 is t1 # same tuple, does so for efficiency, it is safe bse tuples cannot be mutated"
   ]
  },
  {
   "cell_type": "code",
   "execution_count": 40,
   "metadata": {},
   "outputs": [
    {
     "data": {
      "text/plain": [
       "1.239500613999553"
      ]
     },
     "execution_count": 40,
     "metadata": {},
     "output_type": "execute_result"
    }
   ],
   "source": [
    "timeit('tuple((1, 2, 3, 4))', number=10_000_000)"
   ]
  },
  {
   "cell_type": "code",
   "execution_count": 42,
   "metadata": {},
   "outputs": [
    {
     "data": {
      "text/plain": [
       "2.2314465689996723"
      ]
     },
     "execution_count": 42,
     "metadata": {},
     "output_type": "execute_result"
    }
   ],
   "source": [
    "timeit('list((1, 2, 3, 4))', number=10_000_000) # slower bse you have to create a new list every time"
   ]
  },
  {
   "cell_type": "code",
   "execution_count": 43,
   "metadata": {},
   "outputs": [],
   "source": [
    "# Storage efficiency"
   ]
  },
  {
   "cell_type": "code",
   "execution_count": 45,
   "metadata": {},
   "outputs": [
    {
     "name": "stdout",
     "output_type": "stream",
     "text": [
      "1 items: 56\n",
      "2 items: 64\n",
      "3 items: 72\n",
      "4 items: 80\n",
      "5 items: 88\n",
      "6 items: 96\n",
      "7 items: 104\n",
      "8 items: 112\n",
      "9 items: 120\n",
      "10 items: 128\n"
     ]
    }
   ],
   "source": [
    "# for a tuple, \n",
    "# when it gets 1 element longer, all it needs is 8 extra bytes\n",
    "for i in range(10):\n",
    "    import sys\n",
    "    c = tuple(range(i+1))\n",
    "    size_c = sys.getsizeof(c)\n",
    "    print(f'{i+1} items: {size_c}')"
   ]
  },
  {
   "cell_type": "code",
   "execution_count": 50,
   "metadata": {},
   "outputs": [
    {
     "name": "stdout",
     "output_type": "stream",
     "text": [
      "200\n",
      "1 items: 96, diff: 95\n",
      "96\n",
      "2 items: 104, diff: 103\n",
      "104\n",
      "3 items: 112, diff: 111\n",
      "112\n",
      "4 items: 120, diff: 119\n",
      "120\n",
      "5 items: 128, diff: 127\n",
      "128\n",
      "6 items: 136, diff: 135\n",
      "136\n",
      "7 items: 144, diff: 143\n",
      "144\n",
      "8 items: 160, diff: 159\n",
      "160\n",
      "9 items: 192, diff: 191\n",
      "192\n",
      "10 items: 200, diff: 199\n"
     ]
    }
   ],
   "source": [
    "# for a list, \n",
    "# when it gets 1 element longer, all it needs is 8 extra bytes\n",
    "for i in range(10):\n",
    "    import sys\n",
    "    c = list(range(i+1))\n",
    "    size_prev = bool(size_c) or 0\n",
    "    size_c = sys.getsizeof(c)\n",
    "    print(f'{i+1} items: {size_c}, diff: {size_c - size_prev}')"
   ]
  },
  {
   "cell_type": "code",
   "execution_count": 47,
   "metadata": {},
   "outputs": [
    {
     "data": {
      "text/plain": [
       "16"
      ]
     },
     "execution_count": 47,
     "metadata": {},
     "output_type": "execute_result"
    }
   ],
   "source": [
    "160 - 144"
   ]
  },
  {
   "cell_type": "code",
   "execution_count": null,
   "metadata": {},
   "outputs": [],
   "source": []
  }
 ],
 "metadata": {
  "kernelspec": {
   "display_name": "Python 3",
   "language": "python",
   "name": "python3"
  },
  "language_info": {
   "codemirror_mode": {
    "name": "ipython",
    "version": 3
   },
   "file_extension": ".py",
   "mimetype": "text/x-python",
   "name": "python",
   "nbconvert_exporter": "python",
   "pygments_lexer": "ipython3",
   "version": "3.7.3"
  }
 },
 "nbformat": 4,
 "nbformat_minor": 2
}
